Coliform/ArduCAM.py
Coliform/DependenciesInstaller.py
Coliform/GUI.py
Coliform/GUItk.py
Coliform/InitialSetup.py
Coliform/MultiPlot.py
Coliform/OneWire.py
Coliform/RGBSensor.py
Coliform/RPiCamera.py
Coliform/RPiCameraBackend.py
Coliform/RPiGPIO.py
Coliform/__init__.py
Coliform-0.7.5.1.dist-info/DESCRIPTION.rst
Coliform-0.7.5.1.dist-info/METADATA
Coliform-0.7.5.1.dist-info/RECORD
Coliform-0.7.5.1.dist-info/WHEEL
Coliform-0.7.5.1.dist-info/metadata.json
Coliform-0.7.5.1.dist-info/top_level.txt
